LICENSE
README.md
setup.py
SearchForThis2/SearchForThis2.py
SearchForThis2/__init__.py
SearchForThis2.egg-info/PKG-INFO
SearchForThis2.egg-info/SOURCES.txt
SearchForThis2.egg-info/dependency_links.txt
SearchForThis2.egg-info/requires.txt
SearchForThis2.egg-info/top_level.txt