Metadata-Version: 2.1
Name: SearchForThis2
Version: 0.1.0
Summary: Projeto final da disciplina de Programação Orientada a Objetos II
Author: Luan
Author-email: luansilva2357@gmail.com
Keywords: python,web,search
Classifier: Intended Audience :: Education
Classifier: Programming Language :: Python :: 3
Requires-Python: >=3.6
License-File: LICENSE
Requires-Dist: googlesearch-python==1.2.3
